{"shard_id":"デジタル社会推進標準ガイドライン_2023-07_36","group":"デジタル社会推進標準ガイドライン_2023-07","chunk_count":50,"chunks":[{"chunk_id":"d1f95f139a828538c65b3330f8867692_c0","doc_id":"d1f95f139a828538c65b3330f8867692","text":"page A ﻿ . ﻿ DS-680.2 ウェブコンテンツガイドライン デジタ ル社会推進標準ガイ ド ライ ン Web Content Guidelines 2025 年 （令和7 年） 9 月30 日 デジタル社会推進会議幹事会決定 Normative\n\npage 1 ﻿ . ﻿ CONTENTS 1 概要 .................................................................................................................................................................................................................................... 6 1.1 適用対象 ......................................................................................................","meeting":"デジタル社会推進標準ガイドライン","agency":"デジタル庁","title":"DS-680.2 ウェブコンテンツガイドライン（PDF／9,200KB）","date":"2023-07-04","url":"https://www.digital.go.jp/assets/contents/node/basic_page/field_ref_resources/e2a06143-ed29-4f1d-9c31-0f06fca67afc/a02f877e/20250930_web_content_guidelines.pdf","page_from":1,"page_to":2,"char_count":1200},{"chunk_id":"d1f95f139a828538c65b3330f8867692_c1","doc_id":"d1f95f139a828538c65b3330f8867692","text":".............................................................. 8 1.4.1 導入のための参考になる文書 . ............................................................................................................... 9 1.4.2 支援ツール ............................................................................................................................................................ 9 1.4.3 利用の手引き . .................................................................................................................","meeting":"デジタル社会推進標準ガイドライン","agency":"デジタル庁","title":"DS-680.2 ウェブコンテンツガイドライン（PDF／9,200KB）","date":"2023-07-04","url":"https://www.digital.go.jp/assets/contents/node/basic_page/field_ref_resources/e2a06143-ed29-4f1d-9c31-0f06fca67afc/a02f877e/20250930_web_content_guidelines.pdf","page_from":2,"page_to":2,"char_count":1200},{"chunk_id":"d1f95f139a828538c65b3330f8867692_c2","doc_id":"d1f95f139a828538c65b3330f8867692","text":".............................................................................................................. 11 2.1 ウェブサイ トの種類 ...................................................................................................................................... 11 2.2 証跡 ......................................................................................................................................................................... 11 2.3 記録管理 ............................................","meeting":"デジタル社会推進標準ガイドライン","agency":"デジタル庁","title":"DS-680.2 ウェブコンテンツガイドライン（PDF／9,200KB）","date":"2023-07-04","url":"https://www.digital.go.jp/assets/contents/node/basic_page/field_ref_resources/e2a06143-ed29-4f1d-9c31-0f06fca67afc/a02f877e/20250930_web_content_guidelines.pdf","page_from":2,"page_to":2,"char_count":1200},{"chunk_id":"d1f95f139a828538c65b3330f8867692_c3","doc_id":"d1f95f139a828538c65b3330f8867692","text":"....................................................................................................... 14 3.3 社会的な有効活用に資する情報 ..................................................................................................... 14 3.4 情報提供の例外 ............................................................................................................................................ 15 4 情報アクセシビリティの確保 .................................................................................................","meeting":"デジタル社会推進標準ガイドライン","agency":"デジタル庁","title":"DS-680.2 ウェブコンテンツガイドライン（PDF／9,200KB）","date":"2023-07-04","url":"https://www.digital.go.jp/assets/contents/node/basic_page/field_ref_resources/e2a06143-ed29-4f1d-9c31-0f06fca67afc/a02f877e/20250930_web_content_guidelines.pdf","page_from":2,"page_to":3,"char_count":1200},{"chunk_id":"d1f95f139a828538c65b3330f8867692_c4","doc_id":"d1f95f139a828538c65b3330f8867692","text":". . ........................................................................................................... 18 5.1 意見・要望等の受付欄の設置 18 5.2 回答集の提供 ................................................................................................................................................. . .................................................................................................................... 18 5.3 ソーシャルメディ アの活用 18 5.4 府省間連携の実施 ...................................................","meeting":"デジタル社会推進標準ガイドライン","agency":"デジタル庁","title":"DS-680.2 ウェブコンテンツガイドライン（PDF／9,200KB）","date":"2023-07-04","url":"https://www.digital.go.jp/assets/contents/node/basic_page/field_ref_resources/e2a06143-ed29-4f1d-9c31-0f06fca67afc/a02f877e/20250930_web_content_guidelines.pdf","page_from":3,"page_to":3,"char_count":1200},{"chunk_id":"d1f95f139a828538c65b3330f8867692_c5","doc_id":"d1f95f139a828538c65b3330f8867692","text":"...................................................................................................................................... 20 7.1.1 デジタルアーカイブにおける二次利用条件の検討 . ........................................................... .................................................................................................... ................................................................................................................ . .......................................................","meeting":"デジタル社会推進標準ガイドライン","agency":"デジタル庁","title":"DS-680.2 ウェブコンテンツガイドライン（PDF／9,200KB）","date":"2023-07-04","url":"https://www.digital.go.jp/assets/contents/node/basic_page/field_ref_resources/e2a06143-ed29-4f1d-9c31-0f06fca67afc/a02f877e/20250930_web_content_guidelines.pdf","page_from":3,"page_to":3,"char_count":1200},{"chunk_id":"d1f95f139a828538c65b3330f8867692_c6","doc_id":"d1f95f139a828538c65b3330f8867692","text":"ゴリ表示 25 8.2.2 こども向けイベン トのユニバーサルアクセスに係る情報提供 .................................. . .......................................................................................................................................................... ........................................................................................................................................................................ 25 9 ...........................................................................................","meeting":"デジタル社会推進標準ガイドライン","agency":"デジタル庁","title":"DS-680.2 ウェブコンテンツガイドライン（PDF／9,200KB）","date":"2023-07-04","url":"https://www.digital.go.jp/assets/contents/node/basic_page/field_ref_resources/e2a06143-ed29-4f1d-9c31-0f06fca67afc/a02f877e/20250930_web_content_guidelines.pdf","page_from":3,"page_to":4,"char_count":1200},{"chunk_id":"d1f95f139a828538c65b3330f8867692_c7","doc_id":"d1f95f139a828538c65b3330f8867692","text":".... ....................................................................................................................................... 27 9.3.1 個人の能力に関する表現 27 9.3.2 年齢に関する表現 27\n\npage 3 ﻿ . ﻿ CONTENTS 9.3.3 ジェンダーとセクシュアリティ ...................................................................................................................... ......................................................................................................................................... . ..............","meeting":"デジタル社会推進標準ガイドライン","agency":"デジタル庁","title":"DS-680.2 ウェブコンテンツガイドライン（PDF／9,200KB）","date":"2023-07-04","url":"https://www.digital.go.jp/assets/contents/node/basic_page/field_ref_resources/e2a06143-ed29-4f1d-9c31-0f06fca67afc/a02f877e/20250930_web_content_guidelines.pdf","page_from":3,"page_to":4,"char_count":1200},{"chunk_id":"d1f95f139a828538c65b3330f8867692_c8","doc_id":"d1f95f139a828538c65b3330f8867692","text":"........ . .................................................................................................................. ................................................................................................................................................................................ 29 9.7 外国国名表記・地名表記 30 9.8 記述・表現の評価と見直し 30 10 多言語対応の推進 31 10.1 機械翻訳等を利用する場合の注意点 .......................................................................................... . .........................","meeting":"デジタル社会推進標準ガイドライン","agency":"デジタル庁","title":"DS-680.2 ウェブコンテンツガイドライン（PDF／9,200KB）","date":"2023-07-04","url":"https://www.digital.go.jp/assets/contents/node/basic_page/field_ref_resources/e2a06143-ed29-4f1d-9c31-0f06fca67afc/a02f877e/20250930_web_content_guidelines.pdf","page_from":4,"page_to":4,"char_count":1200},{"chunk_id":"d1f95f139a828538c65b3330f8867692_c9","doc_id":"d1f95f139a828538c65b3330f8867692","text":".......................... ..................................................................................... 32 11.1 生成AI 等の信頼性確保 32 11.2 生成AI 利用時の著作権の適正な取扱い 32 11.3 生成AIを機械翻訳に用いることの明示 32 11.4 生成AIの利用に係るコンテンツの信頼性確保 .................................................................... ........................................................................................................................................... ........................................................................","meeting":"デジタル社会推進標準ガイドライン","agency":"デジタル庁","title":"DS-680.2 ウェブコンテンツガイドライン（PDF／9,200KB）","date":"2023-07-04","url":"https://www.digital.go.jp/assets/contents/node/basic_page/field_ref_resources/e2a06143-ed29-4f1d-9c31-0f06fca67afc/a02f877e/20250930_web_content_guidelines.pdf","page_from":4,"page_to":5,"char_count":1200},{"chunk_id":"d1f95f139a828538c65b3330f8867692_c10","doc_id":"d1f95f139a828538c65b3330f8867692","text":"......... . .................................................................................... 地域別の情報提供 36 13.1 地域区分 36 13.1.1 地理的条件を加味した区分の追加設置 36\n\npage 4 ﻿ . ﻿ CONTENTS 14 . ................................................................................................................................................................... ............................................................................................. ................................................................","meeting":"デジタル社会推進標準ガイドライン","agency":"デジタル庁","title":"DS-680.2 ウェブコンテンツガイドライン（PDF／9,200KB）","date":"2023-07-04","url":"https://www.digital.go.jp/assets/contents/node/basic_page/field_ref_resources/e2a06143-ed29-4f1d-9c31-0f06fca67afc/a02f877e/20250930_web_content_guidelines.pdf","page_from":4,"page_to":5,"char_count":1200},{"chunk_id":"d1f95f139a828538c65b3330f8867692_c11","doc_id":"d1f95f139a828538c65b3330f8867692","text":"............................................................................................................................................................ 39 15.1 サービスカタログの提供 39 15.1.1 利用者・利用目的別のサービスカタログにおける機能 39 16 公開情報の品質確保 40 16.1 データ品質の確保 ....................................................................................................................................... .......................................................................................................................","meeting":"デジタル社会推進標準ガイドライン","agency":"デジタル庁","title":"DS-680.2 ウェブコンテンツガイドライン（PDF／9,200KB）","date":"2023-07-04","url":"https://www.digital.go.jp/assets/contents/node/basic_page/field_ref_resources/e2a06143-ed29-4f1d-9c31-0f06fca67afc/a02f877e/20250930_web_content_guidelines.pdf","page_from":5,"page_to":5,"char_count":1200},{"chunk_id":"d1f95f139a828538c65b3330f8867692_c12","doc_id":"d1f95f139a828538c65b3330f8867692","text":".... ..................................................................................................................................... .................................................................................................................................... 41 16.1.5 正確性 （Accurate） 41 16.1.6 完全性 （Complete） 41 16.1.7 一貫性 （Consistent） .................................................................................................................................. . ..................","meeting":"デジタル社会推進標準ガイドライン","agency":"デジタル庁","title":"DS-680.2 ウェブコンテンツガイドライン（PDF／9,200KB）","date":"2023-07-04","url":"https://www.digital.go.jp/assets/contents/node/basic_page/field_ref_resources/e2a06143-ed29-4f1d-9c31-0f06fca67afc/a02f877e/20250930_web_content_guidelines.pdf","page_from":5,"page_to":5,"char_count":1200},{"chunk_id":"d1f95f139a828538c65b3330f8867692_c13","doc_id":"d1f95f139a828538c65b3330f8867692","text":"............................................................ ........................................................................................................ 42 16.3 情報の有効性に関する情報の明示 42 17 ウェブコンテンツのライフサイクル管理 43 17.1 ウェブコンテンツのライフサイクルの期間 . ................................................................................ . .................................................................................. . .......................................................................................","meeting":"デジタル社会推進標準ガイドライン","agency":"デジタル庁","title":"DS-680.2 ウェブコンテンツガイドライン（PDF／9,200KB）","date":"2023-07-04","url":"https://www.digital.go.jp/assets/contents/node/basic_page/field_ref_resources/e2a06143-ed29-4f1d-9c31-0f06fca67afc/a02f877e/20250930_web_content_guidelines.pdf","page_from":5,"page_to":6,"char_count":1200},{"chunk_id":"d1f95f139a828538c65b3330f8867692_c14","doc_id":"d1f95f139a828538c65b3330f8867692","text":"....................................................... ............................................................................................................................................ ............................................................................................................................................ 記録管理 45 18.1 記録管理の要件 45 18.2 内容情報の付与 46 18.2.1 表現情報の付与 ...........................................................................................................","meeting":"デジタル社会推進標準ガイドライン","agency":"デジタル庁","title":"DS-680.2 ウェブコンテンツガイドライン（PDF／9,200KB）","date":"2023-07-04","url":"https://www.digital.go.jp/assets/contents/node/basic_page/field_ref_resources/e2a06143-ed29-4f1d-9c31-0f06fca67afc/a02f877e/20250930_web_content_guidelines.pdf","page_from":6,"page_to":6,"char_count":1200},{"chunk_id":"d1f95f139a828538c65b3330f8867692_c15","doc_id":"d1f95f139a828538c65b3330f8867692","text":"............................................................................................................................ ............................................................................................................................................ ...................................................................................................................................... 47 18.3.4 来歴情報の提供 47 18.3.5 不変性情報の提供 47 19 ウェブサイ トによる情報提供に伴う料金 ....................................","meeting":"デジタル社会推進標準ガイドライン","agency":"デジタル庁","title":"DS-680.2 ウェブコンテンツガイドライン（PDF／9,200KB）","date":"2023-07-04","url":"https://www.digital.go.jp/assets/contents/node/basic_page/field_ref_resources/e2a06143-ed29-4f1d-9c31-0f06fca67afc/a02f877e/20250930_web_content_guidelines.pdf","page_from":6,"page_to":6,"char_count":1200},{"chunk_id":"d1f95f139a828538c65b3330f8867692_c16","doc_id":"d1f95f139a828538c65b3330f8867692","text":"......................................................................... ................................................................................................................................................................................................................................. 48 20 本ガイ ドラインの遵守状況の確認 49 21 付録 50 20.1 リンク集 50 索引 51\n\npage 6 1. 概要 1 概要 本ガイドラインは、各府省が設置・公開するウェブサイトに掲載するコンテンツの品質確保、メタデータ定 義等の情報管理及び文章表現に関する指針をまとめている。 1.1 適用対象 本ガイドラインは、各府省がウェブサイト等による行政情報及び機能提供を、より充実し利","meeting":"デジタル社会推進標準ガイドライン","agency":"デジタル庁","title":"DS-680.2 ウェブコンテンツガイドライン（PDF／9,200KB）","date":"2023-07-04","url":"https://www.digital.go.jp/assets/contents/node/basic_page/field_ref_resources/e2a06143-ed29-4f1d-9c31-0f06fca67afc/a02f877e/20250930_web_content_guidelines.pdf","page_from":6,"page_to":7,"char_count":1112},{"chunk_id":"d1f95f139a828538c65b3330f8867692_c17","doc_id":"d1f95f139a828538c65b3330f8867692","text":"府省がウェブサイトを通じて発信する情報は増加してきたが、 それに伴い、 情 報の探索や検索、管理が難しくなってきている。そこで本ガイドラインは、前掲の各ガイドラインを引き継ぎ ながら、様々な組織がウェブサイトを通じ発信する情報を、同じ原則・ルールに基づいて取扱えるようにする こと、以下の観点からウェブサイトへの掲載方法や表現を見直し、中長期の品質確保を目指すための指針を示 すことを目的としている。\n\npage 7 1. 概要 ●情報の信頼性向上 ●一元的管理 ●検索性の向上 ●技術選定コストの低減 ●情報の利用負荷の削減 ●発信コストの削減 ●情報の維持コストの低減 また、 社会の多様化により、 ニーズに合致する情報の掲示、 平易かつ簡潔な構成、 用語及び文章の利用といっ た、利用者視点での分かりやすい情報発信が求められていることから、本ガイドラインでは、ウェブサイトの 種類毎に最低限掲出すべき情報、文章表現等の指針を定めている。 1.3 記述範囲と構成 本ガイドラインでは、主に以下の指針を記載している。 ●ウェブサイト等により提供する情報の種類に関する指針 ［3章］ ●情報アクセシビ","meeting":"デジタル社会推進標準ガイドライン","agency":"デジタル庁","title":"DS-680.2 ウェブコンテンツガイドライン（PDF／9,200KB）","date":"2023-07-04","url":"https://www.digital.go.jp/assets/contents/node/basic_page/field_ref_resources/e2a06143-ed29-4f1d-9c31-0f06fca67afc/a02f877e/20250930_web_content_guidelines.pdf","page_from":7,"page_to":9,"char_count":1283},{"chunk_id":"d1f95f139a828538c65b3330f8867692_c18","doc_id":"d1f95f139a828538c65b3330f8867692","text":"本ガイドラインと、特に関係する内容を含む文書は、以下のとおり。なお、本文中で密接に関係する文書が ある場合は参照箇所をあわせて記載している。 ●「DS-670.1 ユーザビリティガイドライン」 （デジタル庁） ウェブサイトを含む情報システムの使いやすさの確保に関するガイドライン。 ●「DS-680.1 ウェブサイトガイドライン」 （デジタル庁） 使いやすいウェブサイトの構築に関するガイドライン。旧 「Webサイト等による行政情報の提供・利用 促進に関するガイドライン」 及び旧 「Webサイトガイドブック」 の内容を引き継ぐ。﻿ ●「Web サイト等の整備及び廃止に係るドメイン管理ガイドライン」 （デジタル庁） ドメインの保有・移行・廃止等の管理に関するガイドライン。以下 「ドメイン管理ガイドライン」 とい う。﻿ ●「みんなの公共サイト運用ガイドライン」 （総務省・2024年版） ウェブアクセシビリティの確保に関するガイドライン。 ●政府機関等のサイバーセキュリティ対策のための統一基準群 （ＮＣＯ） ウェブサイトを含む情報システムのセキュリティの確保に関するガイドライン。 以下 「統一","meeting":"デジタル社会推進標準ガイドライン","agency":"デジタル庁","title":"DS-680.2 ウェブコンテンツガイドライン（PDF／9,200KB）","date":"2023-07-04","url":"https://www.digital.go.jp/assets/contents/node/basic_page/field_ref_resources/e2a06143-ed29-4f1d-9c31-0f06fca67afc/a02f877e/20250930_web_content_guidelines.pdf","page_from":9,"page_to":10,"char_count":1260},{"chunk_id":"d1f95f139a828538c65b3330f8867692_c19","doc_id":"d1f95f139a828538c65b3330f8867692","text":"ン関連ガイドラインの読み進め方・資料の探し方」 （デジタル庁） 1.5 利用と配布 本ガイドラインに掲載・発信している情報の著作権は、特記されていない限りデジタル庁に帰属し、特段の 権利表記がない限り、 「公共データ利用規約 （第1.0版） ※1」 （PDL1.0） 又は互換性のある 「CC﻿BY﻿4.0 （クリエイティ ブコモンズ （CC） ﻿-表示﻿4.0﻿国際） 」 に従う範囲で利用できる。PDL1.0﻿のうち、 本サイト独自の出典記載例や本ルー ルの適用を受けないコンテンツ等サイトによって内容が異なる部分の情報については 「コンテンツの利用に係 るPDL1.0に関する重要情報※2」 を参照すること。 コピーライトポリシー （デジタル庁） ※3 ※1 公共データ利用規約 （第1.0版） https://www.digital.go.jp/resources/open_data/public_data_license_v1.0 ※2 コンテンツの利用に係るPDL1.0に関する重要情報 https://www.digital.go.jp/copyright-policy#import","meeting":"デジタル社会推進標準ガイドライン","agency":"デジタル庁","title":"DS-680.2 ウェブコンテンツガイドライン（PDF／9,200KB）","date":"2023-07-04","url":"https://www.digital.go.jp/assets/contents/node/basic_page/field_ref_resources/e2a06143-ed29-4f1d-9c31-0f06fca67afc/a02f877e/20250930_web_content_guidelines.pdf","page_from":10,"page_to":12,"char_count":1200},{"chunk_id":"d1f95f139a828538c65b3330f8867692_c20","doc_id":"d1f95f139a828538c65b3330f8867692","text":"律第88号） 第2条第1項の定義による ●処分：行政手続法 （平成5年法律第88号） 第2条第2項の定義による ●行政指導：行政手続法 （平成5年法律第88号） 第2条第6項の定義による ●命令等：行政手続法 （平成5年法律第88号） 第2条第8項の定義による ●前各項の他、法令において公表等が義務付けられている情報 ●前各項の他、制度、指針等に基づき公表する情報 ●前各項の他、官報に掲載することができる情報 ●前各項の他、以下の性質を有する情報 ●情報の公衆送信時点又は効力の発生時点を明確化する必要があるもの ●初出時点からの更改や修正が、報道や広く国民生活に影響する下記のもの ■報道発表 ■統計資料 ■会見録\n\npage 12 2. 用語 ■会議等の議事録及び配布資料 ●表1 （注記） に掲げる、PDFやePub等の形式でパッケージ化された各種出版物又は電子出版物 注記） 本資料種別は以下の規定類を参照した上で、頻出するものを独自に追加している。 ●国立国会図書館法第25条の3第3項のインターネット資料等に関する件 （平成22年1月22日国立国会図書 館告示第1号） ●国立国会図書","meeting":"デジタル社会推進標準ガイドライン","agency":"デジタル庁","title":"DS-680.2 ウェブコンテンツガイドライン（PDF／9,200KB）","date":"2023-07-04","url":"https://www.digital.go.jp/assets/contents/node/basic_page/field_ref_resources/e2a06143-ed29-4f1d-9c31-0f06fca67afc/a02f877e/20250930_web_content_guidelines.pdf","page_from":12,"page_to":13,"char_count":1200},{"chunk_id":"d1f95f139a828538c65b3330f8867692_c21","doc_id":"d1f95f139a828538c65b3330f8867692","text":"l 目録・データカタログ Inventory 目録及び書誌類 国会関係資料 （注記） Diet 議会資料 基本計画 BasicPlan 基本計画書 政策評価 PolicyEvaluation 政策評価書 論文 AcademicPaper 学術上の論文に係る出版物 広報 PR 広報資料 行事 Event 講演会、展示会等の関係資 料 会議等 Council 審議会等の関係資料 地図・海図 Map 表2-3 地図・海図 調査報告書 Report 調査報告書 表2-7 委託による調査研 究報告書類 その他 Other その他各号に準ずる出版物 注記） 国会関係資料とは、行政機関が保有するものを限定して指す。\n\npage 13 2. 用語 2.3 記録管理 現在及び将来への説明責任及び利用ニーズを確実に効果的かつ効率的に果たすため、適切な権限、基準及び 手順に基づいて、公開するべき情報を特定・収集・整理し、定められた期間の公開維持、保守を行い、不要に なった場合安全に廃棄すること。\n\npage 14 3. ウェブサイ ト等により提供する情報の種類 3 ウェブサイ ト等により提供する情報の種類 ","meeting":"デジタル社会推進標準ガイドライン","agency":"デジタル庁","title":"DS-680.2 ウェブコンテンツガイドライン（PDF／9,200KB）","date":"2023-07-04","url":"https://www.digital.go.jp/assets/contents/node/basic_page/field_ref_resources/e2a06143-ed29-4f1d-9c31-0f06fca67afc/a02f877e/20250930_web_content_guidelines.pdf","page_from":13,"page_to":16,"char_count":1197},{"chunk_id":"d1f95f139a828538c65b3330f8867692_c22","doc_id":"d1f95f139a828538c65b3330f8867692","text":"収集、 蓄積している電子情報 （データベースを含む。 ） のうち、国民、企業等からの利用の要望が多い情報又は健全な社会・経済活動に有益な情報について、ウェブ サイト等を通じ、積極的に提供する。﻿\n\npage 15 3. ウェブサイ ト等により提供する情報の種類 3.4 情報提供の例外 前各項は、国民、企業等第三者に不利益が生じ又は行政活動に重大な支障が生じるおそれがある場合、適用 を除外される。﻿\n\npage 16 4. 情報アクセシビリティ の確保 4 情報アクセシビリティの確保 4.1 多様なアクセス手段の提供 各府省は、主利用者のニーズに応じて自組織が保有・発信する情報への多様なアクセス手段の提供に努める。 アクセス手段とは、以下に例示する手段を指す。 ●利用者別メニュー、利用目的別サイトの設置 ●検索サービス、レファレンスサービスの提供 ●物理的な閲覧が制限された資料のデジタル化資料の提供 ●メールやRSSによる新着・更新通知 ●AI等の活用を含む情報検索の補助 4.1.1 情報アクセシビリティの確保における環境整備 各府省は、 「障害者による情報の取得及び利用並びに意思疎通に","meeting":"デジタル社会推進標準ガイドライン","agency":"デジタル庁","title":"DS-680.2 ウェブコンテンツガイドライン（PDF／9,200KB）","date":"2023-07-04","url":"https://www.digital.go.jp/assets/contents/node/basic_page/field_ref_resources/e2a06143-ed29-4f1d-9c31-0f06fca67afc/a02f877e/20250930_web_content_guidelines.pdf","page_from":15,"page_to":19,"char_count":1280},{"chunk_id":"d1f95f139a828538c65b3330f8867692_c23","doc_id":"d1f95f139a828538c65b3330f8867692","text":"明があった場合は、読み書 きの支援 （代読・代筆） 等の合理的配慮 （障害を理由とする差別の解消の推進に関する法律第7条2項） を行う。﻿\n\npage 18 5. 国民等との間における双方向の情報流通の確保 5 国民等との間における双方向の情報流通の確保 各府省は、 各府省のウェブサイト等に設けられている国民等からの提供情報を受け付ける窓口を活用して、 所 管行政に関する意見・要望等の収集を図る。﻿ 5.1 意見・要望等の受付欄の設置 ﻿各府省は、主要な施策、事業等の創設、変更等に関する情報を掲載する場合には、それぞれ意見・要望等の 受付欄を設ける。﻿ 5.2 回答集の提供 各府省は、重要な提供情報や頻度の高い質問等に対しては、各府省の考え方、対応等について説明する欄を 設ける。﻿ 5.3 ソーシャルメディ アの活用 各府省は、情報や映像等の交換を行うソーシャルメディアを使用した、国民等への情報提供及び双方向の情 報流通を推進する。﻿ 5.4 府省間連携の実施 各府省のウェブサイト等に他府省の所管行政に関する意見・要望等があった場合は、当該意見・要望等に係 る所管府省が特定することがで","meeting":"デジタル社会推進標準ガイドライン","agency":"デジタル庁","title":"DS-680.2 ウェブコンテンツガイドライン（PDF／9,200KB）","date":"2023-07-04","url":"https://www.digital.go.jp/assets/contents/node/basic_page/field_ref_resources/e2a06143-ed29-4f1d-9c31-0f06fca67afc/a02f877e/20250930_web_content_guidelines.pdf","page_from":18,"page_to":21,"char_count":1200},{"chunk_id":"d1f95f139a828538c65b3330f8867692_c24","doc_id":"d1f95f139a828538c65b3330f8867692","text":"必要なPC ・ スマート フォ ン等の条件 ウェブアクセシビリティ 必須 「みんなの公共サイト運用ガイドライン」 （総務 省・ 2024 年版） に基づく ウェブアクセシビリティ の確保・維持・向上に向けた取組に関する情報 コピーライトポリシー （著 作権について） 推奨 「公共データ利用規約」に基づいた、著作権 及び二次利用等についての情報 ソーシャルメディアポリ シー アカウントがある場合は必須 公式に運営しているソーシャルメディアアカウ ント及び運用方針についての情報 利用規約 利用に際し、利用規約への同 意を求める場合は必須 ウェブサイトの利用規約 プライバシーポリシー 個人情報を取り扱う場合は必 須 個人情報保護に関する情報 特定個人情報等に関する 情報 特定個人情報等を取り扱う場 合は必須 特定個人情報の取扱いに関する告知 サイトマップ 必須 掲載事項の一覧 7.1 コピーライ トポリシー （著作権について ） 各府省は、 ［6 著作物に関する統一的な利用ルールの適用］ に基づく著作物の二次利用を円滑に進めるため、 ウェブサイトに掲載された情報の利用条件を定めたコピーライト","meeting":"デジタル社会推進標準ガイドライン","agency":"デジタル庁","title":"DS-680.2 ウェブコンテンツガイドライン（PDF／9,200KB）","date":"2023-07-04","url":"https://www.digital.go.jp/assets/contents/node/basic_page/field_ref_resources/e2a06143-ed29-4f1d-9c31-0f06fca67afc/a02f877e/20250930_web_content_guidelines.pdf","page_from":21,"page_to":22,"char_count":1200},{"chunk_id":"d1f95f139a828538c65b3330f8867692_c25","doc_id":"d1f95f139a828538c65b3330f8867692","text":"定義 体系 教育利用 非商用 利用 商用利用 cc0 CC0 PD ツール 利用可 利用可 利用可 pdm PDM （パブリックドメインマー ク） ﻿ PD ツール 利用可 利用可 利用可 ccby CC﻿BY （表示） ﻿ クリエイティブコモンズ （CC） ﻿ 利用可 利用可 利用可 ccbysa CC﻿BY-SA （表示- 継承） ﻿ クリエイティブコモンズ （CC） ﻿ 利用可 利用可 利用可 ccbynd CC﻿BY-ND （表示- 改変禁止） ﻿ クリエイティブコモンズ （CC） ﻿ 条件付き で可 条件付き で可 条件付き で可 ccbync CC﻿BY-NC （表示- 非営利） ﻿ クリエイティブコモンズ （CC） ﻿ 利用可 利用可 不可 ccbyncsa CC﻿BY-NC-SA （表示- 非営利- 継承） ﻿ クリエイティブコモンズ （CC） ﻿ 利用可 利用可 不可 ccbyncnd CC﻿BY-NC-ND （表示- 非営利- 改変禁止） ﻿ クリエイティブコモンズ （CC） ﻿ 条件付き で可 条件付き で可 不可 incr 著作権あり Rights Statem","meeting":"デジタル社会推進標準ガイドライン","agency":"デジタル庁","title":"DS-680.2 ウェブコンテンツガイドライン（PDF／9,200KB）","date":"2023-07-04","url":"https://www.digital.go.jp/assets/contents/node/basic_page/field_ref_resources/e2a06143-ed29-4f1d-9c31-0f06fca67afc/a02f877e/20250930_web_content_guidelines.pdf","page_from":22,"page_to":23,"char_count":1130},{"chunk_id":"d1f95f139a828538c65b3330f8867692_c26","doc_id":"d1f95f139a828538c65b3330f8867692","text":"リシーでPDL以外のライセンスを採用している場合、個別の資料にPDLを適用することも可能である。 7.2 ソーシャルメディ アポリシー 各府省は、ソーシャルメディア （SNS） を通じた情報発信の正確性や信頼性確保のため、ソーシャルメディア を運用する場合は、 各府省が当該アカウントを運用していることを確認することができる措置として、 公式ソー シャルメディアアカウントの運用方針を策定・公表する。﻿ ●組織が運営しているソーシャルメディアアカウントの一覧 ●運用方法 （発信する情報や、SNSの各機能の利用方針） ●免責事項 ●利用者による書き込みに対する方針 ●発信情報の利用条件 （コピーライトポリシー） ●短縮URLの利用に関する表明 ●運用方法の周知・変更等に関する方針の表明 ●利用にあたり留意すべき事項 ●問合せ先 ソーシャルメディアの利用にあたっては、統一基準における遵守事項 「ソーシャルメディアによる情報発信 時の対策」 の規定もあわせて参照すること。﻿ 7.3 ウェブアクセシビリティ方針及び試験結果 各府省は、 「みんなの公共サイト運用ガイドライン」 （総務省・2024年版","meeting":"デジタル社会推進標準ガイドライン","agency":"デジタル庁","title":"DS-680.2 ウェブコンテンツガイドライン（PDF／9,200KB）","date":"2023-07-04","url":"https://www.digital.go.jp/assets/contents/node/basic_page/field_ref_resources/e2a06143-ed29-4f1d-9c31-0f06fca67afc/a02f877e/20250930_web_content_guidelines.pdf","page_from":23,"page_to":25,"char_count":1219},{"chunk_id":"d1f95f139a828538c65b3330f8867692_c27","doc_id":"d1f95f139a828538c65b3330f8867692","text":"のイベント への参加のしやすさを判断できるようになっているか\n\npage 24 8. 利用者視点での情報提供 参考例 項目 記載内容 イベントの名称 内容がわかりやすいタイトルを記載する 対象となる施設や アクティビティ 見学や体験等のように、対象となる施設や体験できるアクティビティが明 確な場合には記載する。記載例： 「職業体験」 「ダム見学」 イベントの内容紹介文 イベントの概要を自由に記載。SNS 等でシェアされる際に簡潔なサマリー が表示できる場合は、サマリー文も用意する 実施場所 イベントが実施される場所について記載する 主催者 （問合せ先） ﻿ 見学・体験の主催者の名称、連絡先を明記する 申込み方法 申込みの有無を示す。申込みが必要な場合は案内を記載 申込み期間・ スケジュール 事前申込みが必要な場合、申込みの受付期間を記載 料金の有無 「有料」 「実費」 「無料」等の料金の有無を明記。民間イベント等、実費を 超える料金を収集する場合は 「有料」と記載 参加条件・対象・持ち物 対象年齢、親子同伴等の参加条件を記載。保護者が用意するべき持ち物 がある場合には具体的に明記 実施","meeting":"デジタル社会推進標準ガイドライン","agency":"デジタル庁","title":"DS-680.2 ウェブコンテンツガイドライン（PDF／9,200KB）","date":"2023-07-04","url":"https://www.digital.go.jp/assets/contents/node/basic_page/field_ref_resources/e2a06143-ed29-4f1d-9c31-0f06fca67afc/a02f877e/20250930_web_content_guidelines.pdf","page_from":24,"page_to":26,"char_count":1199},{"chunk_id":"d1f95f139a828538c65b3330f8867692_c28","doc_id":"d1f95f139a828538c65b3330f8867692","text":"な人が参加できるよう工夫する。こ どもに障害のあるケースだけではなく、保護者に障害のあるケースを想定して記述すること。﻿ ●イベントの会場へのアクセスしやすさ （車椅子やベビーカーでの経路） ●授乳室等の有無 ●手話通訳付きのツアーの有無 ●多言語対応の有無 ●感覚過敏のある人へのイヤーマフやフィジェット等の提供の有無 ●会場の明るさや騒がしさ、空間の閉鎖性や開放性 （閉所・暗所・高所等の有無） ●イベント最中の発声や入退室等の可否\n\npage 26 9. 言語・文章構成及び表現 9 言語・文章構成及び表現 9.1 原則 各府省は、 ウェブサイトを通じた広く一般に向けた情報発信において、 「公用文作成の考え方」 （文化審議会建 議） に基づき、 ウェブサイトの媒体特性を活かした表現を行う。具体的には、 各府省は利用ニーズに応じて、 以 下の各原則を満たした文章表現・文章構成等に取り組む。﻿ ●プレインランゲージ ●インクルーシブランゲージ ●やさしい日本語 ●図・表・写真・音声・動画等の活用 ●文章表現・装飾におけるアクセシビリティ ●記述・表現の継続的な評価と見直し ●外国国名表記・","meeting":"デジタル社会推進標準ガイドライン","agency":"デジタル庁","title":"DS-680.2 ウェブコンテンツガイドライン（PDF／9,200KB）","date":"2023-07-04","url":"https://www.digital.go.jp/assets/contents/node/basic_page/field_ref_resources/e2a06143-ed29-4f1d-9c31-0f06fca67afc/a02f877e/20250930_web_content_guidelines.pdf","page_from":26,"page_to":28,"char_count":1284},{"chunk_id":"d1f95f139a828538c65b3330f8867692_c29","doc_id":"d1f95f139a828538c65b3330f8867692","text":"●健康状態や病気、怪我等に触れる必要がある場合に、主観的な価値表現を、その表現を用いることに合 理的な理由がある時以外は用いない。主観的な価値表現とは、 「苦しんでいる」 「悩んでいる」 というよう な表現のことを指す。この表現は障害等に苦しんでいることが暗黙の前提となっているが、すべての人 がそうではない。 「筋萎縮性側索硬化症 （ALS） に罹っている」 等の中立な表現を用いるのが適切である。 ●不必要にも拘らず対比的表現を用いない。例えば 「健常者」 という表現は、その障害のないことを基準 とした考え方である。統計資料等で比較に用いる必要がある時など、表現が適切な場合を除き、原則と して用いない。 不適切な例 ●高機能の障害・低機能の障害 ●いつも移動が辛い車椅子の利用者 9.3.2 年齢に関する表現 年齢に関する情報や表現を取り扱う場合、以下に配慮する。 ●主観的な価値表現を用いない。 ●合理的な必然性がない限り、アンケート等で年齢に関する情報を取得しない 不適切な例 ●高齢者でも簡単に使える\n\npage 28 9. 言語・文章構成及び表現 9.3.3 ジェンダーとセクシュアリ","meeting":"デジタル社会推進標準ガイドライン","agency":"デジタル庁","title":"DS-680.2 ウェブコンテンツガイドライン（PDF／9,200KB）","date":"2023-07-04","url":"https://www.digital.go.jp/assets/contents/node/basic_page/field_ref_resources/e2a06143-ed29-4f1d-9c31-0f06fca67afc/a02f877e/20250930_web_content_guidelines.pdf","page_from":28,"page_to":30,"char_count":1228},{"chunk_id":"d1f95f139a828538c65b3330f8867692_c30","doc_id":"d1f95f139a828538c65b3330f8867692","text":"ドライン」 （文化庁） 等を参考にすること。 9.5 図・表・写真・音声・動画等の活用 各府省は、できるだけ図・表・写真・音声・動画等を利用する等、分かりやすい表現方法の活用を推進する。 9.6 文章表現・装飾におけるアクセシビリティ 各府省は、スクリーンリーダー等を用いている読者や、多様な色覚特性 （赤色系を識別しにくい人等） に配慮す るため、アクセシビリティに配慮した文章表現・装飾に努める。﻿ 代表例 ●「丸いボタン」 「赤文字の箇所」 「図の右上」 等、色や形や位置にのみに依拠した表現を使わない ●「あとア」 「1と一」 のように読み上げたときに違いが判別できない行頭記号を併置しない ●太字での強調表現をしたいときは、strong要素等の適切なマークアップを行う ●強調表現のために下線を使わない ●赤文字等の多様な色覚特性のある人に配慮していない表現を使わない 詳しくは 「DS-671.2﻿ウェブアクセシビリティ導入ガイドブック」 （デジタル庁） 及び 「DS-672.1﻿ウェブアクセ シビリティ広報向けガイドブック」 （デジタル庁） を参考にすること。﻿\n\npage 30 9","meeting":"デジタル社会推進標準ガイドライン","agency":"デジタル庁","title":"DS-680.2 ウェブコンテンツガイドライン（PDF／9,200KB）","date":"2023-07-04","url":"https://www.digital.go.jp/assets/contents/node/basic_page/field_ref_resources/e2a06143-ed29-4f1d-9c31-0f06fca67afc/a02f877e/20250930_web_content_guidelines.pdf","page_from":30,"page_to":32,"char_count":1143},{"chunk_id":"d1f95f139a828538c65b3330f8867692_c31","doc_id":"d1f95f139a828538c65b3330f8867692","text":".1 機械翻訳等を利用する場合の注意点 機械翻訳を用いるときは、正確性が保証されていないことを明示するよう努める。 10.2 機械翻訳等における専門用語の取扱い 特定の用語に対する対訳が定まっている場合は、辞書データを整備するなどの適切な対応を行うよう努める。 なお、非専門家向けに情報を提供する場合は、 ［9.2.2 非専門家向けの情報提供・申請手続における法律等の表 現］ に準じた対応に努める。 10.3 機械翻訳等の利用に係るウェブアクセシビリティの確保 画像の代替テキストを含むウェブページの多言語化等を行うことで、代替テキストのウェブアクセシビリ ティの確保が難しくなる場合 （注記） は、ページ冒頭等のスクリーンリーダー利用者が確実に認知できる場所に、 画像に含まれる画像化された文字と、代替テキストが一致しない可能性があること等の注意喚起を行うよう努 める。﻿ 記載例 This﻿page﻿uses﻿machine﻿translation.﻿Please﻿note﻿that﻿the﻿translation﻿may﻿not﻿be﻿completely﻿accurate,﻿or﻿ ch","meeting":"デジタル社会推進標準ガイドライン","agency":"デジタル庁","title":"DS-680.2 ウェブコンテンツガイドライン（PDF／9,200KB）","date":"2023-07-04","url":"https://www.digital.go.jp/assets/contents/node/basic_page/field_ref_resources/e2a06143-ed29-4f1d-9c31-0f06fca67afc/a02f877e/20250930_web_content_guidelines.pdf","page_from":32,"page_to":33,"char_count":1278},{"chunk_id":"d1f95f139a828538c65b3330f8867692_c32","doc_id":"d1f95f139a828538c65b3330f8867692","text":"を用いたコンテンツには、生成AIを使用していること、当該情報の翻訳の精度を利用者自 身の責任で判断する必要があることを明示するよう努める。﻿ 誤訳や不正確な訳を回避するべき用語等がある場合は、 ［10.2 機械翻訳等における専門用語の取扱い］ に準じ 辞書データを整備する。 記載例 この翻訳はAIによる自動翻訳であり、正確性を欠く場合があります。翻訳の妥当性や信頼性をご確認の上で ご利用ください。﻿\n\npage 33 11. 生成AI 等の利用時の信頼性確保 11.4 生成AIの利用に係るコンテンツの信頼性確保 生成AIを用いてコンテンツのテキスト本文、字幕、クローズドキャプション及び代替テキスト等を生成又は 翻訳する場合、生成AIを使用していること、当該情報の翻訳の精度を利用者自身の責任で判断する必要がある ことを、利用者が確実に認知できる形式で明示するよう努める。﻿\n\npage 34 12. 本省サイ トにおける情報提供 12 本省サイ トにおける情報提供 各府省は、 ［3.1 行政の諸活動に関する情報の提供］ に従い、自組織の活動や所管法令等の情報を広く利用者 に供する場合、 利","meeting":"デジタル社会推進標準ガイドライン","agency":"デジタル庁","title":"DS-680.2 ウェブコンテンツガイドライン（PDF／9,200KB）","date":"2023-07-04","url":"https://www.digital.go.jp/assets/contents/node/basic_page/field_ref_resources/e2a06143-ed29-4f1d-9c31-0f06fca67afc/a02f877e/20250930_web_content_guidelines.pdf","page_from":33,"page_to":36,"char_count":1271},{"chunk_id":"d1f95f139a828538c65b3330f8867692_c33","doc_id":"d1f95f139a828538c65b3330f8867692","text":"催する催事等の日程 会議等 Councils 組織が開催する会議体に関する日程・場所の情 報\n\npage 35 12. 本省サイ トにおける情報提供 大分類 中分類 英語表記 説明 調達 Procurement 調達に関する情報 採用 Recruitment 人材の採用に関するもの 公募 Public Offering 公募に関するもの 施設 Location 施設の所在地・利用案内に関するもの。名称を出 すのが適切な場合はラベルを柔軟に変更可能 法令 Law 法令に関する情報 通知・通達・処分 Official Notification 通知・通達・行政処分・行政指導等に関する情報 政策 Policy 組織が所管し ている政策に関する情報 政策分野 任意 政策分野を定めている場合記載 制度 System 各政策に紐づく制度 申請・ 手続 Application 申請・届出等の手続に関する情報 サービス Services 主としてウェブアプリケーションやアプリを介し提 供されるもの。サービスカタログ 情報公開 Disclosure 情報公開、公文書管理 資料・ 刊行物 Resource","meeting":"デジタル社会推進標準ガイドライン","agency":"デジタル庁","title":"DS-680.2 ウェブコンテンツガイドライン（PDF／9,200KB）","date":"2023-07-04","url":"https://www.digital.go.jp/assets/contents/node/basic_page/field_ref_resources/e2a06143-ed29-4f1d-9c31-0f06fca67afc/a02f877e/20250930_web_content_guidelines.pdf","page_from":35,"page_to":37,"char_count":1199},{"chunk_id":"d1f95f139a828538c65b3330f8867692_c34","doc_id":"d1f95f139a828538c65b3330f8867692","text":"地域区分］ に定める9地域区分を利用することを原則とし、 地方支部等の設置状況に応じた区分や都道府県毎の区分等をその必要に応じ提供する。 13.1 地域区分 地域 URI 対象となる都道府県 北海道 hokkaido 北海道 東北 tohoku 青森、岩手、宮城、秋田、山形、福島 関東甲信 kanto-koshin 茨城、栃木、群馬、山梨、長野、埼玉、千葉、東京、神奈川 北陸 hokuriku 新潟、富山、石川、福井 東海 tokai 岐阜、静岡、愛知、三重 近畿 kinki 滋賀、京都、大阪、兵庫、奈良、和歌山 中国 chugoku 鳥取、島根、岡山、広島、山口 四国 shikoku 徳島、香川、愛媛、高知 九州・沖縄 kyushu-okinawa 福岡、佐賀、長崎、熊本、大分、宮崎、鹿児島、沖縄 13.1.1 地理的条件を加味した区分の追加設置 気象情報や災害に関連した情報等を提供する場合は 「奄美地方」 や 「小笠原諸島」 等、地理的条件を加味した 区分をその必要に応じ提供できる。﻿\n\npage 37 14. オープンデータの推進 14 オープンデータの推進 各府省は、行政機関の","meeting":"デジタル社会推進標準ガイドライン","agency":"デジタル庁","title":"DS-680.2 ウェブコンテンツガイドライン（PDF／9,200KB）","date":"2023-07-04","url":"https://www.digital.go.jp/assets/contents/node/basic_page/field_ref_resources/e2a06143-ed29-4f1d-9c31-0f06fca67afc/a02f877e/20250930_web_content_guidelines.pdf","page_from":37,"page_to":38,"char_count":1256},{"chunk_id":"d1f95f139a828538c65b3330f8867692_c35","doc_id":"d1f95f139a828538c65b3330f8867692","text":"を参考にすること。なお、 e-govデータポータルに提供されたデータはジャパンサーチ （注記） に連携されることにも留意して整備すること。﻿ 注記） ﻿ ジャパンサーチは、デジタルアーカイブ推進に関する検討会 （事務局 ： 内閣府知的財産戦略推進事務局） の方 針のもと、さまざまな分野の機関の連携・協力により、国立国会図書館がシステムを運用している、デ ジタルアーカイブの分野横断プラットフォーム。﻿\n\npage 38 14. オープンデータの推進 14.1.2 個別データセッ トや資料群に関するメタデータの整備 データカタログに採録されたデータセットや資料群 （コレクション） の内容や所在情報を提供する場合、横断 検索における検索性や二次利用における利便性向上の観点から、資料のタイトル、寄与者、作成日等の基本的 なメタデータを共通に付与するよう努める。詳しくは、 「参考資料 （ウェブコンテンツ） ﻿メタデータ定義サンプル」 （デジタル庁） を参考にすること。﻿\n\npage 39 15. 行政情報の一元的・総合的な提供 15 行政情報の一元的・総合的な提供 各府省は、各府省における登録、","meeting":"デジタル社会推進標準ガイドライン","agency":"デジタル庁","title":"DS-680.2 ウェブコンテンツガイドライン（PDF／9,200KB）","date":"2023-07-04","url":"https://www.digital.go.jp/assets/contents/node/basic_page/field_ref_resources/e2a06143-ed29-4f1d-9c31-0f06fca67afc/a02f877e/20250930_web_content_guidelines.pdf","page_from":38,"page_to":41,"char_count":1263},{"chunk_id":"d1f95f139a828538c65b3330f8867692_c36","doc_id":"d1f95f139a828538c65b3330f8867692","text":"フォーマットの変更等がウェブサイトで公開している情報に与える変化を管理 し、将来にわたっても情報の再生及び意味の理解ができるように、ウェブコンテンツについて、以下に定める 適切な管理に努める。﻿﻿﻿﻿ 16.1 データ品質の確保 各府省はウェブサイトで公開している情報について最新の日本産業規格を踏まえ、各情報の特性を考慮した データ品質維持に努めることで、当該情報の信用価値を損なわないようにする。﻿ 具体的には、各府省は、策定したプロジェクト目標の達成の観点から、下記の例示を参考に、ウェブサイト 及び掲載コンテンツに要求されるデータ品質を定義し、適切な運用に取り組む。﻿ 16.1.1 帰属性 （Attributable） 当該情報を、誰が・いつ作成したのかを明示すること。 16.1.2 判読性 （Legible） 当該情報を読んだときに （読んだ人にとって） 内容が適切に判断・理解できること。判読性を高めるための基 準については ［9 言語・文章構成及び表現］ を参照すること。 16.1.3 適時性 （Contemporaneous） 情報の作成に関連する活動とその記録が合理的な期間内","meeting":"デジタル社会推進標準ガイドライン","agency":"デジタル庁","title":"DS-680.2 ウェブコンテンツガイドライン（PDF／9,200KB）","date":"2023-07-04","url":"https://www.digital.go.jp/assets/contents/node/basic_page/field_ref_resources/e2a06143-ed29-4f1d-9c31-0f06fca67afc/a02f877e/20250930_web_content_guidelines.pdf","page_from":41,"page_to":43,"char_count":1205},{"chunk_id":"d1f95f139a828538c65b3330f8867692_c37","doc_id":"d1f95f139a828538c65b3330f8867692","text":"。 16.1.9 可用性 （Available） その情報へアクセスする権限のある人が、権限のレベルに応じて、そのデータに （検索手段の提供などを通じ） 確実にアクセスしたり編集できること。﻿\n\npage 42 16. 公開情報の品質確保 16.2 最新性の確保 各府省は、ウェブサイトによる時宜を得た情報提供を行うとともに、ウェブサイトの掲載情報の内容につい て最新の状態を維持管理するよう努める。﻿ 特に、報道発表資料やその他国民等に速やかに提供することが重要な情報は、原則として、公表日等に提供 するよう努め、それが困難な場合においても、公表日等以降、可及的速やかにウェブサイトで提供するよう努 める。﻿ 16.3 情報の有効性に関する情報の明示 各府省は、廃止等の理由で現在は有効ではないが、社会的にアクセス性を担保しなければならない情報につ いて、利用者に対し当該情報の有効性を判断するための情報を分かりやすく提示するよう努める。﻿ ●廃止された会議体 ●旧会議体 （他の会議体に引き継がれた会議体） ●廃止された文書 ●旧文書 （後続文書が出た文書） ●組織の統廃合 ●政策の統廃合 ●法","meeting":"デジタル社会推進標準ガイドライン","agency":"デジタル庁","title":"DS-680.2 ウェブコンテンツガイドライン（PDF／9,200KB）","date":"2023-07-04","url":"https://www.digital.go.jp/assets/contents/node/basic_page/field_ref_resources/e2a06143-ed29-4f1d-9c31-0f06fca67afc/a02f877e/20250930_web_content_guidelines.pdf","page_from":42,"page_to":44,"char_count":1171},{"chunk_id":"d1f95f139a828538c65b3330f8867692_c38","doc_id":"d1f95f139a828538c65b3330f8867692","text":"等のアーカイブに収録されて いることが明らかなとき （注記） 2. 当該情報の根拠となる主たる行政文書が、 各府省の定める文書管理規則保存期間基準を経過し、 移管又 は廃棄の処理が行われていることが明らかなとき 注記） ﻿ ウェブコンテンツの受入先となるアーカイブの収集方針 ・ 手続 ・ 受入れに必要な期間等に留意し、余裕を 持ってアーカイブの保有機関への通知 ・ 受入れに関する協議を行うこと。なお、 移管後のアーカイブに収 録されたコンテンツについては、可能な限り国民によるウェブでのアクセスが継続されるよう、PDL1.0、 CC﻿0やCC﻿BY等の二次利用しやすい利用規約を予め適用しておくことや、アーカイブ上でのインター ネット公開の許諾等の適切な措置を実施することが望ましい。また、 WARPでは （その時点の） トップペー ジ等の主要なページが収集されていることが明らかでも、下位のページやファイルは技術的な問題によ り収集できていないことがあるため、非掲載化又は削除に当たっては、個々のファイルの単位で収録有 無を確認することが望ましい。﻿\n\npage 44 17. ウェブコンテンツ","meeting":"デジタル社会推進標準ガイドライン","agency":"デジタル庁","title":"DS-680.2 ウェブコンテンツガイドライン（PDF／9,200KB）","date":"2023-07-04","url":"https://www.digital.go.jp/assets/contents/node/basic_page/field_ref_resources/e2a06143-ed29-4f1d-9c31-0f06fca67afc/a02f877e/20250930_web_content_guidelines.pdf","page_from":44,"page_to":47,"char_count":1277},{"chunk_id":"d1f95f139a828538c65b3330f8867692_c39","doc_id":"d1f95f139a828538c65b3330f8867692","text":"報 （18.3） ●パッケージ化情報 （注記） 図18.1 ﻿﻿ 注記） 内容情報・保存記述情報等をパッケージ化に際して一覧としてまとめたもの。\n\npage 46 18. 記録管理 18.2 内容情報の付与 18.2.1 表現情報の付与 どのような形式と構造でコンテンツが記述され、再生にはどのようなソフトウェアが必要かを示す。複数の 文書間に親子関係等の構造がある場合は、そのことも示す必要がある。﻿ ●再生方法、フォーマット ●言語 ●他の文書との関係 （文書群の構造） 18.3 保存記述情報の付与 コンテンツの信頼性を示すための過去から現在までの変遷、コンテンツへのアクセス権限、コンテンツの文 脈を示す情報を付与する。﻿ 18.3.1 参照情報の付与 コンテンツにアクセスするための識別子を付与する。通知・通達の文書番号等が参照情報にあたる。各情報 をウェブ上から参照可能にするためには、ウェブ上でも一意のURIを持つ必要がある。﻿ 18.3.2 永続的管理の必要な文書の把握 証跡が半永続的に参照される必要がある場合には、コンテンツのアクセス先のURIが変更されても、永続的 アクセスを可","meeting":"デジタル社会推進標準ガイドライン","agency":"デジタル庁","title":"DS-680.2 ウェブコンテンツガイドライン（PDF／9,200KB）","date":"2023-07-04","url":"https://www.digital.go.jp/assets/contents/node/basic_page/field_ref_resources/e2a06143-ed29-4f1d-9c31-0f06fca67afc/a02f877e/20250930_web_content_guidelines.pdf","page_from":46,"page_to":49,"char_count":1272},{"chunk_id":"d1f95f139a828538c65b3330f8867692_c40","doc_id":"d1f95f139a828538c65b3330f8867692","text":"インに沿ったウェブサイトによる情報提供は、行政の透明性向上や行政情報の有効活用の観点か らの行政施策として行うものであることから、国民等一般に対して提供する情報については、原則として無償 で提供する。﻿﻿﻿﻿﻿ ただし、情報を利用することにより利益を受ける者が特定の者に限られ、ウェブサイトによる提供に係る経 費として相当の額を要する場合においては、原則として提供に係る経費の実費を利用者負担とする。この場合 においても、以下のような観点で、一定のタイミングでの見直しを図る。﻿ ●安価かつ安全な最新技術を活用することによる、提供に係る経費の低減化の検討 ●利用者を増加させ、個別の利用者の負担額を低減する取組の検討 ●利用者負担での提供とすることが社会的経済的に適当かどうかの再検討\n\npage 49 20. 本ガイ ドラインの遵守状況の確認 20 本ガイドラインの遵守状況の確認 各府省における本ガイドラインの遵守状況については、当該府省自らが適切に確認する。\n\npage 50 21. 付録 21 付録 21.1 リンク集 本ガイドラインで言及しているウェブページ等の一覧を以下に示す。 利用・","meeting":"デジタル社会推進標準ガイドライン","agency":"デジタル庁","title":"DS-680.2 ウェブコンテンツガイドライン（PDF／9,200KB）","date":"2023-07-04","url":"https://www.digital.go.jp/assets/contents/node/basic_page/field_ref_resources/e2a06143-ed29-4f1d-9c31-0f06fca67afc/a02f877e/20250930_web_content_guidelines.pdf","page_from":49,"page_to":52,"char_count":1200},{"chunk_id":"d1f95f139a828538c65b3330f8867692_c41","doc_id":"d1f95f139a828538c65b3330f8867692","text":"46 ⸺の保存記述情報の付与 46 た行 データ品質の確保 ⸺：帰属性 （Attributable） … ………………………………… ………………………………………… …………………………… … …………………………………… … …………………………………… 40 ⸺：判読性 （Legible） 40 ⸺：適時性 （Contemporaneous） 40 ⸺：原本性 （Original） 41 ⸺：正確性 （Accurate） 41 ⸺：完全性 （Complete） ……………………………………… … ………………………………… ……………………………………… … …………………………………… 41 ⸺：一貫性 （Consistent） 41 ⸺：永続性 （Enduring） 41 ⸺：可用性 （Available） 41 は行 プレインランゲージ ⸺に関する説明… ………………………………………… … ………………………………………… 26 や行 やさしい日本語 ⸺に関する説明 29","meeting":"デジタル社会推進標準ガイドライン","agency":"デジタル庁","title":"DS-680.2 ウェブコンテンツガイドライン（PDF／9,200KB）","date":"2023-07-04","url":"https://www.digital.go.jp/assets/contents/node/basic_page/field_ref_resources/e2a06143-ed29-4f1d-9c31-0f06fca67afc/a02f877e/20250930_web_content_guidelines.pdf","page_from":52,"page_to":52,"char_count":449},{"chunk_id":"85d49d8312776e72b4b77c63d51606fc_c0","doc_id":"85d49d8312776e72b4b77c63d51606fc","text":"page A ﻿ . ﻿ ユーザビリティ導入ガイ ドブック DS-671.1 デジタ ル社会推進実践ガイ ドブ ッ ク Introduction to Usability 2025 年 （令和7 年） 10 月16 日 技術検討会議サービスデザイ ンタスク フ ォー ス Informative\n\npage 1 ﻿ . ﻿ CONTENTS 1 概要 ..................................................................................................................................................................................................................................... 6 1.1 標準ガイ ドラインにおける本文書の位置づけ ..................................................................","meeting":"デジタル社会推進標準ガイドライン","agency":"デジタル庁","title":"DS-671.1 ユーザビリティ導入ガイドブック（PDF／10,594KB）","date":"2023-07-04","url":"https://www.digital.go.jp/assets/contents/node/basic_page/field_ref_resources/e2a06143-ed29-4f1d-9c31-0f06fca67afc/91365885/20251016_introduction_to_usability.pdf","page_from":1,"page_to":2,"char_count":1200},{"chunk_id":"85d49d8312776e72b4b77c63d51606fc_c1","doc_id":"85d49d8312776e72b4b77c63d51606fc","text":"......................... 7 1.4.1 導入のための参考になる文書 . ............................................................................................................... 7 1.4.2 利用の手引き . ...................................................................................................................................................... 7 1.5 記述範囲と構成 . ................................................................................................................................................ 8 1.6 利用と","meeting":"デジタル社会推進標準ガイドライン","agency":"デジタル庁","title":"DS-671.1 ユーザビリティ導入ガイドブック（PDF／10,594KB）","date":"2023-07-04","url":"https://www.digital.go.jp/assets/contents/node/basic_page/field_ref_resources/e2a06143-ed29-4f1d-9c31-0f06fca67afc/91365885/20251016_introduction_to_usability.pdf","page_from":2,"page_to":2,"char_count":1200},{"chunk_id":"85d49d8312776e72b4b77c63d51606fc_c2","doc_id":"85d49d8312776e72b4b77c63d51606fc","text":"...... 9 2.1 ユーザビリティ とはなにか ........................................................................................................................ 9 2.1.1 ユーザビリティ の観点 ................................................................................................................................ 10 2.1.2 利用者 . ................................................................................................................................................................... 11 2.1.3 使用エラー （ユースエラー） ","meeting":"デジタル社会推進標準ガイドライン","agency":"デジタル庁","title":"DS-671.1 ユーザビリティ導入ガイドブック（PDF／10,594KB）","date":"2023-07-04","url":"https://www.digital.go.jp/assets/contents/node/basic_page/field_ref_resources/e2a06143-ed29-4f1d-9c31-0f06fca67afc/91365885/20251016_introduction_to_usability.pdf","page_from":2,"page_to":2,"char_count":1200},{"chunk_id":"85d49d8312776e72b4b77c63d51606fc_c3","doc_id":"85d49d8312776e72b4b77c63d51606fc","text":"............................................................ 15 2.5 認知とバイアス . ............................................................................................................................................... 16 2.5.1 文脈効果 .............................................................................................................................................................. 16 2.5.2 デザインモデルとメンタルモデル ................................................................................","meeting":"デジタル社会推進標準ガイドライン","agency":"デジタル庁","title":"DS-671.1 ユーザビリティ導入ガイドブック（PDF／10,594KB）","date":"2023-07-04","url":"https://www.digital.go.jp/assets/contents/node/basic_page/field_ref_resources/e2a06143-ed29-4f1d-9c31-0f06fca67afc/91365885/20251016_introduction_to_usability.pdf","page_from":2,"page_to":3,"char_count":1200},{"chunk_id":"85d49d8312776e72b4b77c63d51606fc_c4","doc_id":"85d49d8312776e72b4b77c63d51606fc","text":"....................................................... 19 3.1.1 ディセプティ ブパターン . ............................................................................................................................ 20 3.2 ユーザビリティ デザインの原則 ........................................................................................................... 21 3.3 アクセシビリティ フ ァース ト ................................................................................................................... 22 3.3.1 アクセシビリティ とは ...","meeting":"デジタル社会推進標準ガイドライン","agency":"デジタル庁","title":"DS-671.1 ユーザビリティ導入ガイドブック（PDF／10,594KB）","date":"2023-07-04","url":"https://www.digital.go.jp/assets/contents/node/basic_page/field_ref_resources/e2a06143-ed29-4f1d-9c31-0f06fca67afc/91365885/20251016_introduction_to_usability.pdf","page_from":3,"page_to":3,"char_count":1200},{"chunk_id":"85d49d8312776e72b4b77c63d51606fc_c5","doc_id":"85d49d8312776e72b4b77c63d51606fc","text":"................................................... 24 3.4.1 ユーザーが行うタスクへの適合性 ................................................................................................... 25 3.4.2 インタラクティ ブシステムの自己記述性の確保 ..................................................................... 26 3.4.3 ユーザーが抱く 期待への一致 ............................................................................................................. 27 3.4.4 ユーザーによる学習性の確保 ................................................................","meeting":"デジタル社会推進標準ガイドライン","agency":"デジタル庁","title":"DS-671.1 ユーザビリティ導入ガイドブック（PDF／10,594KB）","date":"2023-07-04","url":"https://www.digital.go.jp/assets/contents/node/basic_page/field_ref_resources/e2a06143-ed29-4f1d-9c31-0f06fca67afc/91365885/20251016_introduction_to_usability.pdf","page_from":3,"page_to":3,"char_count":1200},{"chunk_id":"85d49d8312776e72b4b77c63d51606fc_c6","doc_id":"85d49d8312776e72b4b77c63d51606fc","text":"................................................................................. 32 3.5.1 気づきやす く する ............................................................................................................................................ 32 3.5.2 注意を逸らさないようにする ................................................................................................................ 33 3.5.3 区別しやす く する .....................................................................................................","meeting":"デジタル社会推進標準ガイドライン","agency":"デジタル庁","title":"DS-671.1 ユーザビリティ導入ガイドブック（PDF／10,594KB）","date":"2023-07-04","url":"https://www.digital.go.jp/assets/contents/node/basic_page/field_ref_resources/e2a06143-ed29-4f1d-9c31-0f06fca67afc/91365885/20251016_introduction_to_usability.pdf","page_from":3,"page_to":3,"char_count":1200},{"chunk_id":"85d49d8312776e72b4b77c63d51606fc_c7","doc_id":"85d49d8312776e72b4b77c63d51606fc","text":".6 人間中心の原則 ............................................................................................................................................ 36 4 ユーザビリティ を確保するデザインプロセス ........................................................................................ 37 4.1 人間中心設計 （Human Centered Design: HCD） . ................................................................. 37 4.1.1 実装前に、 利用者による試験を繰り返し実施する 「ダブル」 V字モデル ............. 38 4.2 ユーザビリティ設計活動で解決すべき課題 . .................................","meeting":"デジタル社会推進標準ガイドライン","agency":"デジタル庁","title":"DS-671.1 ユーザビリティ導入ガイドブック（PDF／10,594KB）","date":"2023-07-04","url":"https://www.digital.go.jp/assets/contents/node/basic_page/field_ref_resources/e2a06143-ed29-4f1d-9c31-0f06fca67afc/91365885/20251016_introduction_to_usability.pdf","page_from":3,"page_to":3,"char_count":1200}],"avg_length":1204.384705882353,"k1":1.5,"b":0.75}