{
  "month": "2023-09",
  "keywords": [
    {
      "term": "タロ",
      "count": 3
    },
    {
      "term": "ム ",
      "count": 3
    },
    {
      "term": "の見",
      "count": 3
    },
    {
      "term": "技術",
      "count": 3
    },
    {
      "term": "有機",
      "count": 3
    },
    {
      "term": "な技",
      "count": 3
    },
    {
      "term": "ノロ",
      "count": 3
    },
    {
      "term": "提案",
      "count": 2
    },
    {
      "term": "後の",
      "count": 2
    },
    {
      "term": "らコ",
      "count": 2
    },
    {
      "term": "の参",
      "count": 2
    },
    {
      "term": "加呼",
      "count": 2
    },
    {
      "term": "ーシアム",
      "count": 2
    },
    {
      "term": "個別",
      "count": 2
    },
    {
      "term": "day",
      "count": 2
    },
    {
      "term": "める",
      "count": 2
    },
    {
      "term": "27",
      "count": 2
    },
    {
      "term": "加を",
      "count": 2
    },
    {
      "term": "等 ",
      "count": 2
    },
    {
      "term": "活動",
      "count": 2
    },
    {
      "term": "報告会",
      "count": 2
    },
    {
      "term": "ジの",
      "count": 2
    },
    {
      "term": "の具",
      "count": 2
    },
    {
      "term": "把握",
      "count": 2
    },
    {
      "term": "他省庁等",
      "count": 2
    },
    {
      "term": "スや連",
      "count": 2
    },
    {
      "term": "た一",
      "count": 2
    },
    {
      "term": "の検",
      "count": 2
    },
    {
      "term": "具体",
      "count": 2
    },
    {
      "term": "グの",
      "count": 2
    },
    {
      "term": "ージ",
      "count": 2
    },
    {
      "term": "地域版",
      "count": 1
    },
    {
      "term": "割 ",
      "count": 1
    },
    {
      "term": "学習",
      "count": 1
    },
    {
      "term": "プサ",
      "count": 1
    },
    {
      "term": "ーキャピ",
      "count": 1
    },
    {
      "term": "得方",
      "count": 1
    },
    {
      "term": "ク化",
      "count": 1
    },
    {
      "term": "始８",
      "count": 1
    },
    {
      "term": "存在",
      "count": 1
    },
    {
      "term": "タル協会",
      "count": 1
    },
    {
      "term": "先端テク",
      "count": 1
    },
    {
      "term": "方法等に",
      "count": 1
    },
    {
      "term": "プ ",
      "count": 1
    },
    {
      "term": "よう",
      "count": 1
    },
    {
      "term": "に共",
      "count": 1
    },
    {
      "term": "促進",
      "count": 1
    },
    {
      "term": "を促",
      "count": 1
    },
    {
      "term": "よる",
      "count": 1
    },
    {
      "term": "等関",
      "count": 1
    }
  ],
  "meetings": [
    {
      "meeting": "デジタル臨時行政調査会",
      "count": 3
    }
  ],
  "doc_count": 1,
  "chunk_count": 3
}