{
  "month": "2023-06",
  "keywords": [
    {
      "term": "条第",
      "count": 945
    },
    {
      "term": "共通",
      "count": 727
    },
    {
      "term": "等 ",
      "count": 459
    },
    {
      "term": "規則",
      "count": 407
    },
    {
      "term": "るこ",
      "count": 406
    },
    {
      "term": "規制",
      "count": 399
    },
    {
      "term": "則 ",
      "count": 389
    },
    {
      "term": "等の",
      "count": 372
    },
    {
      "term": "条項",
      "count": 365
    },
    {
      "term": "し否",
      "count": 364
    },
    {
      "term": "条の",
      "count": 347
    },
    {
      "term": "知通",
      "count": 316
    },
    {
      "term": "出又",
      "count": 315
    },
    {
      "term": "通達",
      "count": 300
    },
    {
      "term": "第1",
      "count": 290
    },
    {
      "term": "12",
      "count": 284
    },
    {
      "term": "の規",
      "count": 282
    },
    {
      "term": "もデ",
      "count": 263
    },
    {
      "term": "法令",
      "count": 254
    },
    {
      "term": "通 ",
      "count": 253
    },
    {
      "term": "第6",
      "count": 253
    },
    {
      "term": "発出",
      "count": 248
    },
    {
      "term": "新規",
      "count": 246
    },
    {
      "term": "法施",
      "count": 243
    },
    {
      "term": "完了",
      "count": 237
    },
    {
      "term": "現在",
      "count": 231
    },
    {
      "term": "規制等の",
      "count": 224
    },
    {
      "term": "行規",
      "count": 223
    },
    {
      "term": "度 ",
      "count": 218
    },
    {
      "term": "第 ",
      "count": 218
    },
    {
      "term": "正 ",
      "count": 214
    },
    {
      "term": "さずとも",
      "count": 198
    },
    {
      "term": "働省",
      "count": 198
    },
    {
      "term": "済産",
      "count": 196
    },
    {
      "term": "項目のア",
      "count": 191
    },
    {
      "term": "の3",
      "count": 191
    },
    {
      "term": "則適",
      "count": 188
    },
    {
      "term": "象条",
      "count": 187
    },
    {
      "term": "査 ",
      "count": 187
    },
    {
      "term": "めの",
      "count": 185
    },
    {
      "term": "とを確認",
      "count": 185
    },
    {
      "term": "項の",
      "count": 184
    },
    {
      "term": "ー ",
      "count": 182
    },
    {
      "term": "の2",
      "count": 181
    },
    {
      "term": "とも",
      "count": 173
    },
    {
      "term": "省 ",
      "count": 173
    },
    {
      "term": "作成",
      "count": 171
    },
    {
      "term": "検査",
      "count": 169
    },
    {
      "term": "工程",
      "count": 166
    },
    {
      "term": "一覧",
      "count": 165
    }
  ],
  "meetings": [
    {
      "meeting": "デジタル臨時行政調査会",
      "count": 1023
    }
  ],
  "doc_count": 1,
  "chunk_count": 1023
}