{
  "month": "2025-06",
  "keywords": [
    {
      "term": "図 ",
      "count": 28
    },
    {
      "term": "ある",
      "count": 19
    },
    {
      "term": "管理",
      "count": 18
    },
    {
      "term": "には",
      "count": 17
    },
    {
      "term": "では",
      "count": 16
    },
    {
      "term": "cd",
      "count": 15
    },
    {
      "term": "よび",
      "count": 15
    },
    {
      "term": "メタ",
      "count": 15
    },
    {
      "term": "スコ",
      "count": 14
    },
    {
      "term": "った",
      "count": 14
    },
    {
      "term": "略 ",
      "count": 14
    },
    {
      "term": "中略",
      "count": 13
    },
    {
      "term": "タデ",
      "count": 12
    },
    {
      "term": "確認",
      "count": 12
    },
    {
      "term": "プラット",
      "count": 11
    },
    {
      "term": "ステ",
      "count": 11
    },
    {
      "term": "依存物の",
      "count": 11
    },
    {
      "term": "制限",
      "count": 11
    },
    {
      "term": "存物",
      "count": 11
    },
    {
      "term": "定す",
      "count": 11
    },
    {
      "term": "テナ",
      "count": 11
    },
    {
      "term": "必要",
      "count": 11
    },
    {
      "term": "の設",
      "count": 11
    },
    {
      "term": "を含",
      "count": 10
    },
    {
      "term": "ファイル",
      "count": 10
    },
    {
      "term": "のリ",
      "count": 9
    },
    {
      "term": "対象",
      "count": 9
    },
    {
      "term": "ける",
      "count": 8
    },
    {
      "term": "用し",
      "count": 8
    },
    {
      "term": "ルで",
      "count": 8
    },
    {
      "term": "えら",
      "count": 8
    },
    {
      "term": "リ及",
      "count": 7
    },
    {
      "term": "フェ",
      "count": 7
    },
    {
      "term": "ェー",
      "count": 7
    },
    {
      "term": "デリバリ",
      "count": 7
    },
    {
      "term": "の担",
      "count": 7
    },
    {
      "term": "にな",
      "count": 7
    },
    {
      "term": "version",
      "count": 7
    },
    {
      "term": "スの",
      "count": 7
    },
    {
      "term": "cosign",
      "count": 7
    },
    {
      "term": "registry",
      "count": 7
    },
    {
      "term": "次に",
      "count": 7
    },
    {
      "term": "仕組",
      "count": 7
    },
    {
      "term": "action",
      "count": 7
    },
    {
      "term": "ジと",
      "count": 6
    },
    {
      "term": "たt",
      "count": 6
    },
    {
      "term": "ウン",
      "count": 6
    },
    {
      "term": "それ",
      "count": 6
    },
    {
      "term": "steps",
      "count": 6
    },
    {
      "term": "true",
      "count": 6
    }
  ],
  "meetings": [
    {
      "meeting": "デジタル社会推進標準ガイドライン",
      "count": 32
    }
  ],
  "doc_count": 1,
  "chunk_count": 32
}