{
  "month": "2025-10",
  "keywords": [
    {
      "term": "の ",
      "count": 697
    },
    {
      "term": "第5",
      "count": 524
    },
    {
      "term": "名 ",
      "count": 435
    },
    {
      "term": "所管",
      "count": 367
    },
    {
      "term": "11",
      "count": 346
    },
    {
      "term": "改正",
      "count": 345
    },
    {
      "term": "ある",
      "count": 343
    },
    {
      "term": "査 ",
      "count": 329
    },
    {
      "term": "達等",
      "count": 323
    },
    {
      "term": "規制等の",
      "count": 298
    },
    {
      "term": "に基",
      "count": 284
    },
    {
      "term": "年度",
      "count": 276
    },
    {
      "term": "型 ",
      "count": 272
    },
    {
      "term": "の実",
      "count": 263
    },
    {
      "term": "規定",
      "count": 258
    },
    {
      "term": "類型",
      "count": 254
    },
    {
      "term": "28",
      "count": 254
    },
    {
      "term": "まで",
      "count": 248
    },
    {
      "term": "労働",
      "count": 244
    },
    {
      "term": "通達等",
      "count": 239
    },
    {
      "term": "める",
      "count": 237
    },
    {
      "term": "17",
      "count": 231
    },
    {
      "term": "に係",
      "count": 231
    },
    {
      "term": "24",
      "count": 221
    },
    {
      "term": "業務",
      "count": 217
    },
    {
      "term": "任 ",
      "count": 210
    },
    {
      "term": "定め",
      "count": 205
    },
    {
      "term": "リスト",
      "count": 205
    },
    {
      "term": "管省",
      "count": 205
    },
    {
      "term": "確定",
      "count": 196
    },
    {
      "term": "いて",
      "count": 193
    },
    {
      "term": "る旨",
      "count": 191
    },
    {
      "term": "等 ",
      "count": 187
    },
    {
      "term": "対象",
      "count": 186
    },
    {
      "term": "しが",
      "count": 183
    },
    {
      "term": "業法",
      "count": 182
    },
    {
      "term": "し完",
      "count": 175
    },
    {
      "term": "19",
      "count": 174
    },
    {
      "term": "管理",
      "count": 165
    },
    {
      "term": "項第",
      "count": 165
    },
    {
      "term": "もの",
      "count": 157
    },
    {
      "term": "等を",
      "count": 156
    },
    {
      "term": "ル技",
      "count": 155
    },
    {
      "term": "特別",
      "count": 154
    },
    {
      "term": "実地",
      "count": 154
    },
    {
      "term": "み ",
      "count": 152
    },
    {
      "term": "ついて",
      "count": 151
    },
    {
      "term": "オンライ",
      "count": 149
    },
    {
      "term": "について",
      "count": 149
    },
    {
      "term": "否 ",
      "count": 148
    }
  ],
  "meetings": [
    {
      "meeting": "デジタル臨時行政調査会",
      "count": 1155
    }
  ],
  "doc_count": 9,
  "chunk_count": 1155
}