{
  "month": "2025-06",
  "keywords": [
    {
      "term": "され",
      "count": 27
    },
    {
      "term": "での",
      "count": 14
    },
    {
      "term": "ツー",
      "count": 14
    },
    {
      "term": "ーク",
      "count": 13
    },
    {
      "term": "およ",
      "count": 13
    },
    {
      "term": "る図",
      "count": 13
    },
    {
      "term": "イン",
      "count": 12
    },
    {
      "term": "ーの",
      "count": 12
    },
    {
      "term": "こで",
      "count": 12
    },
    {
      "term": "プラット",
      "count": 11
    },
    {
      "term": "ステ",
      "count": 11
    },
    {
      "term": "ため",
      "count": 11
    },
    {
      "term": "ンチ",
      "count": 10
    },
    {
      "term": "ー ",
      "count": 10
    },
    {
      "term": "性の",
      "count": 9
    },
    {
      "term": "リバ",
      "count": 9
    },
    {
      "term": "取得",
      "count": 9
    },
    {
      "term": "それ",
      "count": 9
    },
    {
      "term": "を取",
      "count": 9
    },
    {
      "term": "に対",
      "count": 9
    },
    {
      "term": "uses",
      "count": 9
    },
    {
      "term": "テム",
      "count": 8
    },
    {
      "term": "リソ",
      "count": 8
    },
    {
      "term": "成果物の",
      "count": 8
    },
    {
      "term": "docker",
      "count": 8
    },
    {
      "term": "らの",
      "count": 8
    },
    {
      "term": "用し",
      "count": 8
    },
    {
      "term": "てい",
      "count": 8
    },
    {
      "term": "示す",
      "count": 7
    },
    {
      "term": "17",
      "count": 7
    },
    {
      "term": "る主",
      "count": 7
    },
    {
      "term": "定 ",
      "count": 7
    },
    {
      "term": "ンの",
      "count": 7
    },
    {
      "term": "自動",
      "count": 7
    },
    {
      "term": "考えられ",
      "count": 7
    },
    {
      "term": "ル ",
      "count": 7
    },
    {
      "term": "cosign",
      "count": 7
    },
    {
      "term": "がある",
      "count": 7
    },
    {
      "term": "次に",
      "count": 7
    },
    {
      "term": "は ",
      "count": 7
    },
    {
      "term": "した",
      "count": 6
    },
    {
      "term": "物と",
      "count": 6
    },
    {
      "term": "ムに",
      "count": 6
    },
    {
      "term": "クト",
      "count": 6
    },
    {
      "term": "ついては",
      "count": 6
    },
    {
      "term": "影響",
      "count": 6
    },
    {
      "term": "critical",
      "count": 6
    },
    {
      "term": "む運",
      "count": 5
    },
    {
      "term": "シナ",
      "count": 5
    },
    {
      "term": "運用保守",
      "count": 5
    }
  ],
  "meetings": [
    {
      "meeting": "デジタル社会推進標準ガイドライン",
      "count": 32
    }
  ],
  "doc_count": 1,
  "chunk_count": 32
}